{
	"info": {
		"_postman_id": "711732bf-f444-43da-bea0-d1a30c92aa02",
		"name": "CQRS",
		"schema": "https://schema.getpostman.com/json/collection/v2.1.0/collection.json",
		"_exporter_id": "12107531"
	},
	"item": [
		{
			"name": "localhost:5000/api/v1/closeBankAccount",
			"request": {
				"method": "DELETE",
				"header": [],
				"body": {
					"mode": "raw",
					"raw": "{\r\n\r\n\"amount\": 70\r\n\r\n}",
					"options": {
						"raw": {
							"language": "json"
						}
					}
				},
				"url": {
					"raw": "http://localhost:5000/api/v1/closeBankAccount/2ce96cdd-08c2-44a0-99c9-dd034e625b58",
					"protocol": "http",
					"host": [
						"localhost"
					],
					"port": "5000",
					"path": [
						"api",
						"v1",
						"closeBankAccount",
						"2ce96cdd-08c2-44a0-99c9-dd034e625b58"
					]
				}
			},
			"response": []
		},
		{
			"name": "http://localhost:5000/api/v1/depositFunds",
			"request": {
				"method": "PUT",
				"header": [],
				"body": {
					"mode": "raw",
					"raw": "{\r\n\r\n\"amount\": 70\r\n\r\n}",
					"options": {
						"raw": {
							"language": "json"
						}
					}
				},
				"url": {
					"raw": "http://localhost:5000/api/v1/depositFunds",
					"protocol": "http",
					"host": [
						"localhost"
					],
					"port": "5000",
					"path": [
						"api",
						"v1",
						"depositFunds"
					]
				}
			},
			"response": []
		},
		{
			"name": "http://localhost:5000/api/v1/openBankAccount",
			"request": {
				"method": "POST",
				"header": [],
				"body": {
					"mode": "raw",
					"raw": "{\r\n\r\n    \"accountHolder\" : \"ex\",\r\n    \"accountType\": \"CURRENT\",\r\n    \"openingBalance\": 50\r\n}",
					"options": {
						"raw": {
							"language": "json"
						}
					}
				},
				"url": {
					"raw": "http://localhost:5000/api/v1/openBankAccount",
					"protocol": "http",
					"host": [
						"localhost"
					],
					"port": "5000",
					"path": [
						"api",
						"v1",
						"openBankAccount"
					]
				}
			},
			"response": []
		}
	]
}